cambai/__init__.py
cambai-0.1.8.dist-info/METADATA
cambai-0.1.8.dist-info/WHEEL
cambai-0.1.8.dist-info/entry_points.txt
cambai-0.1.8.dist-info/RECORD
