Metadata-Version: 2.1
Name: cambai
Version: 0.1.8
Summary: Camb AI API Python Library
Home-page: https://github.com/cr2007/cambai
Author: Chandrashekhar R
Author-email: hi.cskhere@gmail.com
Requires-Python: >=3.8,<4.0
Classifier: Programming Language :: Python :: 3
Classifier: Programming Language :: Python :: 3.8
Classifier: Programming Language :: Python :: 3.9
Classifier: Programming Language :: Python :: 3.10
Classifier: Programming Language :: Python :: 3.11
Classifier: Programming Language :: Python :: 3.12
Requires-Dist: pydantic (>=2.7.1,<3.0.0)
Requires-Dist: requests (>=2.32.2,<3.0.0)
Requires-Dist: rich (>=13.7.1,<14.0.0)
Requires-Dist: tqdm (>=4.66.4,<5.0.0)
Project-URL: Repository, https://github.com/cr2007/cambai
